[
  {
    "patternKey": "error-pattern.tool.tool-exec-failed",
    "reviewer": "user",
    "decision": "approve",
    "timestamp": "2026-03-09T15:51:40.309Z",
    "notes": "Verified pattern - root cause is missing workdir validation"
  },
  {
    "patternKey": "error-pattern.tool.phase-7b-synthetic-review-wrapper-test",
    "reviewer": "agent-phase7b-test",
    "decision": "defer",
    "reason": "Need one more occurrence",
    "timestamp": "2026-03-09T23:50:32.942Z"
  },
  {
    "patternKey": "error-pattern.tool.phase-7b-synthetic-review-wrapper-test",
    "reviewer": "agent-phase7b-test",
    "decision": "approve",
    "timestamp": "2026-03-09T23:50:32.947Z",
    "notes": "Synthetic verification approval"
  },
  {
    "patternKey": "error-pattern.tool.phase-7b-synthetic-review-wrapper-test-p",
    "reviewer": "agent-phase7b-test",
    "decision": "defer",
    "reason": "Need one more occurrence",
    "timestamp": "2026-03-09T23:50:58.292Z"
  },
  {
    "patternKey": "error-pattern.tool.phase-7b-synthetic-review-wrapper-test-p",
    "reviewer": "agent-phase7b-test",
    "decision": "approve",
    "timestamp": "2026-03-09T23:50:59.498Z",
    "notes": "Synthetic verification approval"
  }
]
